linkurious/__init__.py
linkurious-0.1.4.dist-info/LICENSE.txt
linkurious-0.1.4.dist-info/WHEEL
linkurious-0.1.4.dist-info/METADATA
linkurious-0.1.4.dist-info/RECORD
