Metadata-Version: 2.1
Name: linkurious
Version: 0.1.4
Summary: Python wrapper around linkurious API
Home-page: https://github.com/openpolis/linkurious/
License: MIT
Author: guglielmo
Author-email: guglielmo@openpolis.it
Requires-Python: >=3.6,<4.0
Classifier: License :: OSI Approved :: MIT License
Classifier: Programming Language :: Python :: 3
Classifier: Programming Language :: Python :: 3.6
Classifier: Programming Language :: Python :: 3.7
Classifier: Programming Language :: Python :: 3.8
Classifier: Programming Language :: Python :: 3.9
Requires-Dist: tortilla (>=0.5.0,<0.6.0)
Project-URL: Repository, https://github.com/openpolis/linkurious/
